discloudapi/__init__.py
discloudapi/discloudapi.py
discloudapi-0.1.2.dist-info/LICENSE
discloudapi-0.1.2.dist-info/METADATA
discloudapi-0.1.2.dist-info/WHEEL
discloudapi-0.1.2.dist-info/top_level.txt
discloudapi-0.1.2.dist-info/RECORD
