Metadata-Version: 2.1
Name: discloudapi
Version: 0.1.2
Summary: Utility to facilitate the use of the DisCloud api
Home-page: https://github.com/GenerosoDEV/discloudapi
Author: Flavio Generoso
Author-email: flavioa.generoso@gmail.com
Project-URL: Bug Tracker, https://github.com/GenerosoDEV/discloudapi/issues
Classifier: Programming Language :: Python :: 3
Classifier: License :: OSI Approved :: MIT License
Classifier: Operating System :: OS Independent
Requires-Python: >=3.6
License-File: LICENSE
